mypackage/__init__.py
mypackage/__version__.py
mypackage/core.py
timefcuk_concourse_ci_test-5.0.dist-info/METADATA
timefcuk_concourse_ci_test-5.0.dist-info/WHEEL
timefcuk_concourse_ci_test-5.0.dist-info/top_level.txt
timefcuk_concourse_ci_test-5.0.dist-info/RECORD
